antio/_version.py
antio/io.py
antio/__init__.py
antio/parser.py
antio/libeep/pyeep.abi3.so
antio/libeep/libEep.dylib
antio/libeep/__init__.py
antio/utils/config.py
antio/utils/__init__.py
antio/utils/_checks.py
antio/_commands/sys_info.py
antio/_commands/__init__.py
antio/_commands/main.py
antio-0.6.1.dist-info/RECORD
antio-0.6.1.dist-info/WHEEL
antio-0.6.1.dist-info/entry_points.txt
antio-0.6.1.dist-info/top_level.txt
antio-0.6.1.dist-info/METADATA
antio-0.6.1.dist-info/licenses/LICENSE
