Metadata-Version: 2.4
Name: antio
Version: 0.6.1
Summary: Python package to handle I/O with the CNT format from ANT Neuro. 
Author-email: Mathieu Scheltienne <mathieu.scheltienne@gmail.com>
Maintainer: Eric Larson
Maintainer-email: Mathieu Scheltienne <mathieu.scheltienne@gmail.com>
License:                     GNU GENERAL PUBLIC LICENSE
Project-URL: documentation, https://github.com/mscheltienne/antio
Project-URL: homepage, https://github.com/mscheltienne/antio
Project-URL: source, https://github.com/mscheltienne/antio
Project-URL: tracker, https://github.com/mscheltienne/antio/issues
Keywords: ant neuro,cnt,eeg,eego,python
Classifier: Natural Language :: English
Classifier: Operating System :: MacOS
Classifier: Operating System :: Microsoft :: Windows
Classifier: Operating System :: Unix
Classifier: Programming Language :: Python :: 3 :: Only
Classifier: Programming Language :: Python :: 3.11
Classifier: Programming Language :: Python :: 3.12
Classifier: Programming Language :: Python :: 3.13
Classifier: Programming Language :: Python :: 3.14
Requires-Python: >=3.11
License-File: LICENSE
Requires-Dist: click
Requires-Dist: numpy<3,>=1.23
Requires-Dist: packaging
Requires-Dist: psutil
Dynamic: license-file
